{
    "name": "UOM",
    "fields": [
        {
            "fieldName": "uomCode",
            "fieldType": "String",
            "fieldValidateRules": [
                "required"
            ]
        },
        {
            "fieldName": "uomDescription",
            "fieldType": "String",
            "fieldValidateRules": [
                "required"
            ]
        }
    ],
    "relationships": [],
    "changelogDate": "20191124093045",
    "javadoc": "UOM Entity.\\n@author Mihindu Karunarathne.",
    "entityTableName": "uom",
    "dto": "no",
    "pagination": "infinite-scroll",
    "service": "serviceClass",
    "jpaMetamodelFiltering": true,
    "fluentMethods": true,
    "readOnly": false,
    "clientRootFolder": "",
    "applications": "*"
}